{"slug":"carmel-in","city":"Carmel","state":"IN","lat":39.9784186,"lon":-86.1283681,"generatedAt":"2026-05-21T05:10:17.351Z","stores":[{"id":"way/583769283","name":"Goodwill","location":{"lat":39.9519885,"lon":-86.3443757},"address":"6065 Main Street, Whitestown, IN","street":"6065 Main Street","locality":"Whitestown","region":"IN","distanceMiles":11.583770710125497,"score":{"total":64.5,"factors":{"medianHomeValue":{"value":423689.8518447623,"normalized":53.31627602379309,"weight":0.4,"contribution":21.326510409517237},"medianHouseholdIncome":{"value":147309.19625056724,"normalized":69.89096928603843,"weight":0.35,"contribution":24.46183925011345},"pctBachelorsPlus":{"value":69.53956754083717,"normalized":99.3422393440531,"weight":0.15,"contribution":14.901335901607965},"medianGrossRent":{"value":1572.1976222987917,"normalized":37.921635752121375,"weight":0.1,"contribution":3.792163575212138}},"catchment":{"tractCount":2,"population":18121}}},{"id":"way/445095239","name":"Goodwill","location":{"lat":40.0067651,"lon":-86.1296059},"address":"15050 Greyhound Court, Carmel, IN","street":"15050 Greyhound Court","locality":"Carmel","region":"IN","openingHours":"Mo-Sa 09:00-21:00;Su 11:00-19:00","website":"https://www.goodwillindy.org/westfield/","phone":"+1-317-844-1021","distanceMiles":1.959671451361503,"score":{"total":57.1,"factors":{"medianHomeValue":{"value":393202.9922909787,"normalized":50.55873084619446,"weight":0.4,"contribution":20.223492338477783},"medianHouseholdIncome":{"value":122642.33594205683,"normalized":55.79562053831819,"weight":0.35,"contribution":19.528467188411366},"pctBachelorsPlus":{"value":64.02883998040467,"normalized":91.46977140057811,"weight":0.15,"contribution":13.720465710086716},"medianGrossRent":{"value":1524.9673883988144,"normalized":35.86814732168758,"weight":0.1,"contribution":3.586814732168758}},"catchment":{"tractCount":12,"population":70390}}},{"id":"node/4929498716","name":"Goodwill","location":{"lat":39.9387027,"lon":-86.23372},"address":"10491 Walnut Creek Drive, Carmel, IN","street":"10491 Walnut Creek Drive","locality":"Carmel","region":"IN","distanceMiles":6.2178656397004195,"score":{"total":56.6,"factors":{"medianHomeValue":{"value":365970.2477607656,"normalized":47.908338379763336,"weight":0.4,"contribution":19.163335351905335},"medianHouseholdIncome":{"value":116918.10840645478,"normalized":52.52463337511701,"weight":0.35,"contribution":18.383621681290954},"pctBachelorsPlus":{"value":64.23718872129709,"normalized":91.76741245899584,"weight":0.15,"contribution":13.765111868849376},"medianGrossRent":{"value":1919.4471842335377,"normalized":53.019442792762504,"weight":0.1,"contribution":5.301944279276251}},"catchment":{"tractCount":7,"population":33316}}},{"id":"node/4966158713","name":"Goodwill","location":{"lat":39.9609758,"lon":-86.1157604},"address":"1122 Keystone Way, Carmel, IN","street":"1122 Keystone Way","locality":"Carmel","region":"IN","distanceMiles":1.3777510513100781,"score":{"total":53.5,"factors":{"medianHomeValue":{"value":345483.43257332256,"normalized":45.781075385322936,"weight":0.4,"contribution":18.312430154129174},"medianHouseholdIncome":{"value":110835.77253581623,"normalized":49.04901287760927,"weight":0.35,"contribution":17.167154507163243},"pctBachelorsPlus":{"value":66.90584041121576,"normalized":95.57977201602253,"weight":0.15,"contribution":14.336965802403379},"medianGrossRent":{"value":1536.020666650496,"normalized":36.34872463697808,"weight":0.1,"contribution":3.6348724636978087}},"catchment":{"tractCount":15,"population":64855}}},{"id":"way/582700699","name":"Goodwill","location":{"lat":39.9730176,"lon":-86.0014867},"address":"12727 Parkside Drive, Fishers, IN","street":"12727 Parkside Drive","locality":"Fishers","region":"IN","distanceMiles":6.728467910966839,"score":{"total":51.2,"factors":{"medianHomeValue":{"value":287209.0035452759,"normalized":38.959395939440476,"weight":0.4,"contribution":15.583758375776192},"medianHouseholdIncome":{"value":115629.26396657027,"normalized":51.78815083804016,"weight":0.35,"contribution":18.125852793314056},"pctBachelorsPlus":{"value":61.12340265677043,"normalized":87.31914665252918,"weight":0.15,"contribution":13.097871997879377},"medianGrossRent":{"value":1698.878419823597,"normalized":43.429496514069434,"weight":0.1,"contribution":4.3429496514069434}},"catchment":{"tractCount":9,"population":57368}}},{"id":"way/1329666837","name":"Goodwill","location":{"lat":40.040655,"lon":-86.1595612},"distanceMiles":4.606143805411006,"score":{"total":49.8,"factors":{"medianHomeValue":{"value":354232.3888626588,"normalized":46.70456171622162,"weight":0.4,"contribution":18.68182468648865},"medianHouseholdIncome":{"value":106588.608656788,"normalized":46.62206208959314,"weight":0.35,"contribution":16.3177217313576},"pctBachelorsPlus":{"value":52.15786072556149,"normalized":74.51122960794498,"weight":0.15,"contribution":11.176684441191748},"medianGrossRent":{"value":1538.07911988788,"normalized":36.438222603820876,"weight":0.1,"contribution":3.6438222603820876}},"catchment":{"tractCount":6,"population":37964}}},{"id":"node/2658950796","name":"Goodwill","location":{"lat":39.9587699,"lon":-86.0383044},"address":"7440 Fishers Station Drive, Fishers, IN","street":"7440 Fishers Station Drive","locality":"Fishers","region":"IN","openingHours":"Mo-Sa 09:00-21:00, Su 11:00-19:00","website":"https://www.goodwillindy.org/","phone":"+1-317-845-9264","distanceMiles":4.958653152531304,"score":{"total":49.7,"factors":{"medianHomeValue":{"value":299366.62600666535,"normalized":40.49034282135303,"weight":0.4,"contribution":16.196137128541213},"medianHouseholdIncome":{"value":109616.89437740867,"normalized":48.35251107280495,"weight":0.35,"contribution":16.92337887548173},"pctBachelorsPlus":{"value":60.68683264386703,"normalized":86.69547520552433,"weight":0.15,"contribution":13.00432128082865},"medianGrossRent":{"value":1514.9038523609997,"normalized":35.4306022765652,"weight":0.1,"contribution":3.5430602276565204}},"catchment":{"tractCount":10,"population":54579}}},{"id":"node/11960201109","name":"Goodwill","location":{"lat":40.0311649,"lon":-85.9917809},"address":"16650 Mercantile Boulevard, Noblesville, IN","street":"16650 Mercantile Boulevard","locality":"Noblesville","region":"IN","distanceMiles":8.095651684223764,"score":{"total":45.4,"factors":{"medianHomeValue":{"value":311129.68899237114,"normalized":41.9135378366508,"weight":0.4,"contribution":16.76541513466032},"medianHouseholdIncome":{"value":99041.70314701913,"normalized":42.3095446554395,"weight":0.35,"contribution":14.808340629403824},"pctBachelorsPlus":{"value":52.25522261632103,"normalized":74.65031802331575,"weight":0.15,"contribution":11.197547703497362},"medianGrossRent":{"value":1295.051482972531,"normalized":25.87180360750135,"weight":0.1,"contribution":2.587180360750135}},"catchment":{"tractCount":6,"population":34797}}},{"id":"way/258010067","name":"Goodwill","location":{"lat":39.8661416,"lon":-86.1241289},"address":"6150 North Keystone Avenue, Indianapolis, IN","street":"6150 North Keystone Avenue","locality":"Indianapolis","region":"IN","distanceMiles":7.760929199699629,"score":{"total":45.4,"factors":{"medianHomeValue":{"value":298952.3366231023,"normalized":40.43920474452708,"weight":0.4,"contribution":16.175681897810833},"medianHouseholdIncome":{"value":91302.05619259145,"normalized":37.8868892529094,"weight":0.35,"contribution":13.260411238518289},"pctBachelorsPlus":{"value":62.58318374986386,"normalized":89.40454821409122,"weight":0.15,"contribution":13.410682232113682},"medianGrossRent":{"value":1290.7404888081103,"normalized":25.68436907861349,"weight":0.1,"contribution":2.568436907861349}},"catchment":{"tractCount":23,"population":75324}}},{"id":"node/5020785020","name":"Goodwill","location":{"lat":39.9138031,"lon":-86.133667},"address":"1520 East 86th Street, Indianapolis, IN","street":"1520 East 86th Street","locality":"Indianapolis","region":"IN","distanceMiles":4.473364204149878,"score":{"total":43.6,"factors":{"medianHomeValue":{"value":328843.6164576398,"normalized":43.95827379314103,"weight":0.4,"contribution":17.583309517256414},"medianHouseholdIncome":{"value":82033.35747572407,"normalized":32.59048998612804,"weight":0.35,"contribution":11.406671495144813},"pctBachelorsPlus":{"value":55.81956424681351,"normalized":79.74223463830502,"weight":0.15,"contribution":11.961335195745752},"medianGrossRent":{"value":1303.5109218572286,"normalized":26.239605298140372,"weight":0.1,"contribution":2.6239605298140374}},"catchment":{"tractCount":16,"population":51899}}},{"id":"way/187778139","name":"Goodwill","location":{"lat":39.9251737,"lon":-86.0335979},"distanceMiles":6.223439160810437,"score":{"total":40.3,"factors":{"medianHomeValue":{"value":248592.37519608557,"normalized":33.62730577425796,"weight":0.4,"contribution":13.450922309703186},"medianHouseholdIncome":{"value":85509.62013860838,"normalized":34.5769257934905,"weight":0.35,"contribution":12.101924027721676},"pctBachelorsPlus":{"value":55.8382955703293,"normalized":79.768993671899,"weight":0.15,"contribution":11.96534905078485},"medianGrossRent":{"value":1349.5824804463057,"normalized":28.242716541143725,"weight":0.1,"contribution":2.824271654114373}},"catchment":{"tractCount":12,"population":58121}}},{"id":"node/5273777830","name":"Goodwill","location":{"lat":39.908272,"lon":-86.0596247},"address":"6302 East 82nd Street, Indianapolis, IN","street":"6302 East 82nd Street","locality":"Indianapolis","region":"IN","openingHours":"Mo-Sa 09:00-21:00; Su 11:00-19:00","distanceMiles":6.062302409373897,"score":{"total":39.8,"factors":{"medianHomeValue":{"value":272013.8406889681,"normalized":36.95214968658762,"weight":0.4,"contribution":14.780859874635048},"medianHouseholdIncome":{"value":78556.12125596819,"normalized":30.603497860553254,"weight":0.35,"contribution":10.711224251193638},"pctBachelorsPlus":{"value":54.57484206091569,"normalized":77.96406008702242,"weight":0.15,"contribution":11.694609013053363},"medianGrossRent":{"value":1303.2673220457295,"normalized":26.229014001988244,"weight":0.1,"contribution":2.6229014001988245}},"catchment":{"tractCount":15,"population":63028}}},{"id":"way/1213481663","name":"Goodwill","location":{"lat":39.8321373,"lon":-86.0247968},"distanceMiles":11.501736180522112,"score":{"total":9.2,"factors":{"medianHomeValue":{"value":112918.16734068499,"normalized":4.486371319924403,"weight":0.4,"contribution":1.794548527969761},"medianHouseholdIncome":{"value":39349.7177527241,"normalized":8.199838715842343,"weight":0.35,"contribution":2.86994355054482},"pctBachelorsPlus":{"value":15.519129922971986,"normalized":22.170185604245695,"weight":0.15,"contribution":3.325527840636854},"medianGrossRent":{"value":975.8705333160217,"normalized":11.994371013740073,"weight":0.1,"contribution":1.1994371013740073}},"catchment":{"tractCount":21,"population":82176}}}]}